ambientika_py/__init__.py
ambientika_py-0.0.5.dist-info/METADATA
ambientika_py-0.0.5.dist-info/WHEEL
ambientika_py-0.0.5.dist-info/licenses/LICENSE
ambientika_py-0.0.5.dist-info/RECORD
